MDIS/__init__.py
MDIS/mdis.py
MDIS/mdis.pyi
mdis_sec-0.1.7.dist-info/licenses/LICENSE
mdis_sec-0.1.7.dist-info/METADATA
mdis_sec-0.1.7.dist-info/WHEEL
mdis_sec-0.1.7.dist-info/top_level.txt
mdis_sec-0.1.7.dist-info/RECORD
