Metadata-Version: 2.4
Name: mdis-sec
Version: 0.1.7
Summary: MDIS - Malware Detection and Identification System.
Author-email: MemeCoder <memecoder17@gmail.com>
License-Expression: Apache-2.0
Project-URL: Homepage, https://github.com/memecoder12345678/mdis
Project-URL: Bug Tracker, https://github.com/memecoder12345678/mdis/issues
Classifier: Programming Language :: Python :: 3
Classifier: Operating System :: OS Independent
Requires-Python: >=3.10
License-File: LICENSE
Dynamic: license-file
